[{"Id":86644,"country":"MR","name":"Zouerate"},{"Id":86645,"country":"MR","name":"Tékane"},{"Id":86646,"country":"MR","name":"Tidjikja"},{"Id":86647,"country":"MR","name":"Sélibaby"},{"Id":86648,"country":"MR","name":"Rosso"},{"Id":86649,"country":"MR","name":"Nouakchott"},{"Id":86650,"country":"MR","name":"Nouadhibou"},{"Id":86651,"country":"MR","name":"Néma"},{"Id":86652,"country":"MR","name":"Kiffa"},{"Id":86653,"country":"MR","name":"Kaédi"},{"Id":86654,"country":"MR","name":"’Elb el Jmel"},{"Id":86655,"country":"MR","name":"Chingueṭṭi"},{"Id":86656,"country":"MR","name":"Barkéwol"},{"Id":86657,"country":"MR","name":"Aioun"},{"Id":86658,"country":"MR","name":"Atar"},{"Id":86659,"country":"MR","name":"Aleg"},{"Id":86660,"country":"MR","name":"Akjoujt"},{"Id":86661,"country":"MR","name":"Arafat"},{"Id":86662,"country":"MR","name":"Tevragh Zeina"},{"Id":86663,"country":"MR","name":"Dar Naim"}]